example/__init__.py
termax/__init__.py
termax/version.py
termax/agent/__init__.py
termax/agent/_claude.py
termax/agent/_gemini.py
termax/agent/_mistral.py
termax/agent/_ollama.py
termax/agent/_openai.py
termax/agent/_qianfan.py
termax/agent/_qianwen.py
termax/agent/types.py
termax/cli/__init__.py
termax/cli/cli.py
termax/cli/utils.py
termax/function/__init__.py
termax/function/base.py
termax/function/openai/__init__.py
termax/function/openai/git.py
termax/function/openai/macos.py
termax/function/openai/shell.py
termax/function/openai/win.py
termax/plugin/__init__.py
termax/plugin/install.py
termax/plugin/uninstall.py
termax/plugin/shell/__init__.py
termax/plugin/shell/bash.py
termax/plugin/shell/fish.py
termax/plugin/shell/zsh.py
termax/pricing/__init__.py
termax/prompt/__init__.py
termax/prompt/memory.py
termax/prompt/prompt.py
termax/prompt/utils.py
termax/utils/__init__.py
termax/utils/config.py
termax/utils/const.py
termax/utils/metadata.py
termax/utils/qa.py
tests/__init__.py
termax-0.1.4.dist-info/LICENSE
termax-0.1.4.dist-info/METADATA
termax-0.1.4.dist-info/WHEEL
termax-0.1.4.dist-info/entry_points.txt
termax-0.1.4.dist-info/top_level.txt
termax-0.1.4.dist-info/RECORD
