Metadata-Version: 2.1
Name: termax
Version: 0.1.4
Summary: Boost your terminal's intelligence with LLM: intuitive command assistance, seamless customization, and predictive next steps at your fingertips.
Home-page: https://github.com/huangyz0918/termax
Download-URL: https://github.com/huangyz0918/termax/archive/refs/heads/main.zip
Author: Yizheng Huang
Author-email: huangyz0918@gmail.com
Keywords: LLM,deep learning,MLOps,shell,neural networks,command line,terminal,autocomplete
Classifier: Development Status :: 5 - Production/Stable
Classifier: Intended Audience :: Education
Classifier: Intended Audience :: Financial and Insurance Industry
Classifier: Intended Audience :: Science/Research
Classifier: Intended Audience :: Developers
Classifier: Intended Audience :: Information Technology
Classifier: License :: OSI Approved :: Apache Software License
Classifier: Programming Language :: Python :: 3
Classifier: Operating System :: OS Independent
License-File: LICENSE
Requires-Dist: openai
Requires-Dist: rich ~=13.7.1
Requires-Dist: click ~=8.1.7
Requires-Dist: inquirer ~=3.2.4
Requires-Dist: pyperclip ~=1.8.2
Requires-Dist: chromadb ~=0.4.24
Requires-Dist: psutil ~=5.9.8
Requires-Dist: instructor ~=0.6.8
Requires-Dist: pydantic ~=2.6.4
Requires-Dist: setuptools ~=68.2.2
